elbo/__init__.py
elbo/__main__.py
elbo/api.py
elbo/connector.py
elbo/main.py
elbo/model.py
elbo/resources.py
elbo/ui.py
elbo/actions/__init__.py
elbo/actions/cp.py
elbo/actions/run.py
elbo/tracker/__init__.py
elbo/tracker/tracker.py
elbo/utils/__init__.py
elbo/utils/date_utils.py
elbo/utils/file_utils.py
elbo/utils/misc_utils.py
elbo/utils/net_utils.py
elbo-0.0.1042.dist-info/LICENSE.txt
elbo-0.0.1042.dist-info/METADATA
elbo-0.0.1042.dist-info/WHEEL
elbo-0.0.1042.dist-info/entry_points.txt
elbo-0.0.1042.dist-info/top_level.txt
elbo-0.0.1042.dist-info/RECORD
