Metadata-Version: 2.1
Name: elbo
Version: 0.0.1042
Summary: ELBO.AI CLI and API - https://elbo.ai
Home-page: https://elbo.ai
Author: ELBO AI, Inc.
Author-email: hi@elbo.ai
Project-URL: Bug Tracker, https://github.com/elbo-ai/elbo-client/issues
Keywords: pip,elbo,training
Classifier: Programming Language :: Python :: 3
Classifier: Development Status :: 5 - Production/Stable
Classifier: Intended Audience :: Science/Research
Classifier: Intended Audience :: Developers
Classifier: Intended Audience :: System Administrators
Classifier: Natural Language :: English
Classifier: Programming Language :: Python
Classifier: Programming Language :: Python :: 3.6
Classifier: Programming Language :: Python :: 3.7
Classifier: License :: OSI Approved :: Apache Software License
Classifier: Operating System :: OS Independent
Requires-Python: >=3.6
License-File: LICENSE.txt
Requires-Dist: click
Requires-Dist: pyyaml
Requires-Dist: coloredlogs
Requires-Dist: shortuuid
Requires-Dist: better-profanity
Requires-Dist: requests
Requires-Dist: halo
Requires-Dist: inquirer
Requires-Dist: setuptools (>=42)
Requires-Dist: wheel
Requires-Dist: tinynetrc
Requires-Dist: tabulate
Requires-Dist: python-dateutil
Requires-Dist: pandas
Requires-Dist: questionary
Requires-Dist: tzlocal
Requires-Dist: paramiko
Requires-Dist: gitpython
Requires-Dist: tqdm
Requires-Dist: setuptools-rust
Requires-Dist: cryptography
Requires-Dist: wandb
Requires-Dist: psutil
Requires-Dist: gpustat
